odoo/addons/delivery_package_type_shipping_weight/README.rst
odoo/addons/delivery_package_type_shipping_weight/__init__.py
odoo/addons/delivery_package_type_shipping_weight/__manifest__.py
odoo/addons/delivery_package_type_shipping_weight/i18n/delivery_package_default_shipping_weight.pot
odoo/addons/delivery_package_type_shipping_weight/i18n/delivery_package_type_shipping_weight.pot
odoo/addons/delivery_package_type_shipping_weight/i18n/it.po
odoo/addons/delivery_package_type_shipping_weight/i18n/tr.po
odoo/addons/delivery_package_type_shipping_weight/models/__init__.py
odoo/addons/delivery_package_type_shipping_weight/models/delivery_carrier.py
odoo/addons/delivery_package_type_shipping_weight/models/sale_order.py
odoo/addons/delivery_package_type_shipping_weight/models/stock_package_type.py
odoo/addons/delivery_package_type_shipping_weight/models/stock_picking.py
odoo/addons/delivery_package_type_shipping_weight/models/stock_quant_package.py
odoo/addons/delivery_package_type_shipping_weight/readme/CONTRIBUTORS.md
odoo/addons/delivery_package_type_shipping_weight/readme/CREDITS.md
odoo/addons/delivery_package_type_shipping_weight/readme/DESCRIPTION.md
odoo/addons/delivery_package_type_shipping_weight/static/description/icon.png
odoo/addons/delivery_package_type_shipping_weight/static/description/index.html
odoo/addons/delivery_package_type_shipping_weight/tests/__init__.py
odoo/addons/delivery_package_type_shipping_weight/tests/test_delivery_package_type_shipping_weight.py
odoo/addons/delivery_package_type_shipping_weight/views/stock_package_type_views.xml
odoo/addons/delivery_package_type_shipping_weight/wizard/__init__.py
odoo/addons/delivery_package_type_shipping_weight/wizard/choose_delivery_package.py
odoo_addon_delivery_package_type_shipping_weight-18.0.1.0.0.3.dist-info/METADATA
odoo_addon_delivery_package_type_shipping_weight-18.0.1.0.0.3.dist-info/WHEEL
odoo_addon_delivery_package_type_shipping_weight-18.0.1.0.0.3.dist-info/top_level.txt
odoo_addon_delivery_package_type_shipping_weight-18.0.1.0.0.3.dist-info/RECORD
